kadmin/__init__.py
kadmin/__init__.pyi
kadmin/_lib.cpython-311-x86_64-linux-musl.so
kadmin/py.typed
kadmin/exceptions/__init__.py
kadmin/exceptions/__init__.pyi
kadmin/exceptions/py.typed
kadmin_local/__init__.py
kadmin_local/__init__.pyi
kadmin_local/_lib.cpython-311-x86_64-linux-musl.so
kadmin_local/py.typed
kadmin_local/exceptions/__init__.py
kadmin_local/exceptions/__init__.pyi
kadmin_local/exceptions/py.typed
python_kadmin_rs.libs/libcom_err-a17f0a2b.so.2.1
python_kadmin_rs.libs/libgcc_s-0cd532bd.so.1
python_kadmin_rs.libs/libgssapi_krb5-fe9dade7.so.2.2
python_kadmin_rs.libs/libgssrpc-a1d46b0c.so.4.2
python_kadmin_rs.libs/libk5crypto-d61acad3.so.3.1
python_kadmin_rs.libs/libkadm5clnt_mit-2a110382.so.12.0
python_kadmin_rs.libs/libkadm5srv_mit-8c61641b.so.12.0
python_kadmin_rs.libs/libkdb5-0b3519c9.so.10.0
python_kadmin_rs.libs/libkeyutils-939fe6df.so.1.10
python_kadmin_rs.libs/libkrb5-4daf5d73.so.3.3
python_kadmin_rs.libs/libkrb5support-53ecc640.so.0.1
python_kadmin_rs-0.6.3.dist-info/METADATA
python_kadmin_rs-0.6.3.dist-info/WHEEL
python_kadmin_rs-0.6.3.dist-info/top_level.txt
python_kadmin_rs-0.6.3.dist-info/RECORD
python_kadmin_rs-0.6.3.dist-info/licenses/LICENSE
