Metadata-Version: 2.4
Name: python-kadmin-rs
Version: 0.6.3
Summary: Python interface to the Kerberos administration interface (kadm5)
Author-email: Marc 'risson' Schmitt <marc.schmitt@risson.space>, authentik community <hello@goauthentik.io>
License-Expression: MIT
Project-URL: Homepage, https://github.com/authentik-community/kadmin-rs
Project-URL: Documentation, https://github.com/authentik-community/kadmin-rs
Project-URL: Repository, https://github.com/authentik-community/kadmin-rs.git
Keywords: krb5,kadmin,kadm5,kerberos
Classifier: Development Status :: 3 - Alpha
Classifier: Intended Audience :: System Administrators
Classifier: Intended Audience :: Developers
Classifier: Operating System :: MacOS
Classifier: Operating System :: POSIX
Classifier: Programming Language :: Python :: 3
Classifier: Programming Language :: Python :: 3.9
Classifier: Programming Language :: Python :: 3.10
Classifier: Programming Language :: Python :: 3.11
Classifier: Programming Language :: Python :: 3.12
Classifier: Programming Language :: Python :: 3.13
Classifier: Programming Language :: Python :: 3.14
Classifier: Programming Language :: Python :: Implementation :: CPython
Classifier: Programming Language :: Python
Classifier: Programming Language :: Rust
Classifier: Topic :: Software Development :: Libraries :: Python Modules
Classifier: Topic :: System :: Systems Administration :: Authentication/Directory
Classifier: Typing :: Typed
Requires-Python: <3.15,>=3.9
License-File: LICENSE
Dynamic: license-file
